ProPythonUtils/__init__.py
ProPythonUtils/__version__.py
ProPythonUtils/baseUtils.py
ProPythonUtils/core.py
ProPythonUtils-1.0.0.dist-info/DESCRIPTION.rst
ProPythonUtils-1.0.0.dist-info/METADATA
ProPythonUtils-1.0.0.dist-info/RECORD
ProPythonUtils-1.0.0.dist-info/WHEEL
ProPythonUtils-1.0.0.dist-info/metadata.json
ProPythonUtils-1.0.0.dist-info/top_level.txt
